{"url": "http://nypost.com/2017/02/08/isis-fighters-call-trumps-travel-order-a-blessed-ban/", "id": "73", "title": "ISIS fighters call Trump\u2019s travel order a \u2018blessed ban\u2019", "text": "ISIS fighters are reportedly hailing President Trump\u2019s executive order on immigration as \u201cthe Blessed Ban\u201d \u2014 saying it proves to their followers that America really does \u201chate\u201d Islam.\n\nA resident in the Iraqi city of Mosul, which is still considered an Islamic State stronghold, told New York Times terror correspondent Rukmini Callimachi that the jihadists have been openly celebrating the ban ever since Trump singed it into effect on Jan. 27.\n\n\u201cThey\u2019ve even coined a phrase for it,\u201d she tweeted Wednesday. \u201c\u2018The Blessed Ban.'\u201d\n\nIraq is one of the seven predominantly Muslim countries \u2014 along with Iran, Libya, Somalia, Sudan, Syria and Yemen \u2014 from which refugees and citizens are temporarily barred from entering.\n\nCallimachi claimed residents in Mosul had been up in arms about Trump\u2019s executive order, while the Islamic State was praising it.\n\n\u201cEverywhere I go, Iraqis want to ask about the visa ban,\u201d she said. \u201cBut here\u2019s the best part. Guess who else is talking about it? ISIS is.\u201d\n\nDescribing why the extremists were calling the order the \u201cBlessed Ban,\u201d Callimachi said her source told her it was because \u201cISIS sees this as their doing.\u201d\n\n\u201cThey succeeded in scaring the daylight out of America,\u201d she explained. \u201cISIS, according to this resident of Western Mosul, thinks their terror tactic worked. They frightened the most powerful man in the world\u2026And they are celebrating, he says, because it proves to their followers that America really does \u2018hate\u2019 Islam.\u201d\n\nWhile the terror group has remained quit on social media since Trump\u2019s travel ban was implemented, experts have said that they are likely in favor of the ban because it will ultimately drive their message home to recruits.\n\n\u201cThe [ISIS] chatrooms have been abuzz about how this shows that there is a clash of civilizations, that Muslims are not welcome in America,\u201d terrorism expert Mia Bloom, of Georgia State University, told Business Insider.", "authors": ["February"], "publish_date": "2017-02-08", "source": "nypost", "top_words": ["america", "travel", "isis", "ban", "state", "told", "mosul", "fighters", "trumps", "order", "terror", "blessed"], "summary": "ISIS fighters are reportedly hailing President Trump\u2019s executive order on immigration as \u201cthe Blessed Ban\u201d \u2014 saying it proves to their followers that America really does \u201chate\u201d Islam.\n\u201c\u2018The Blessed Ban.\nCallimachi claimed residents in Mosul had been up in arms about Trump\u2019s executive order, while the Islamic State was praising it.\nISIS is.\u201dDescribing why the extremists were calling the order the \u201cBlessed Ban,\u201d Callimachi said her source told her it was because \u201cISIS sees this as their doing.\u201d\u201cThey succeeded in scaring the daylight out of America,\u201d she explained.\n\u201cISIS, according to this resident of Western Mosul, thinks their terror tactic worked."}