{"url": "http://www.latimes.com/opinion/op-ed/la-oe-bad-passports-muslim-ban-20170205-story.html", "id": "469", "title": "Dear Americans: Trump's travel ban is an outrage, but we're used to it", "text": "Trump's executive order has now made entering the United States even more difficult, both for international tourists who hope to travel here, and for those who hope to live here, some of whom have already put in the significant time and effort to do so legally. It pays no heed to the lives it touches. If the order stands, a large number of foreign citizens who are already living in the U.S. legally will get a taste of the undocumented life and learn firsthand what it means to be unwanted, disrespected, and unable to leave without fear of deportation.", "authors": ["Atossa Abrahamian"], "publish_date": "2017-02-05", "source": "latimes", "top_words": ["travel", "legally", "hope", "ban", "unable", "dear", "united", "trumps", "outrage", "unwanted", "order", "undocumented", "americans", "tourists", "used"], "summary": "Trump's executive order has now made entering the United States even more difficult, both for international tourists who hope to travel here, and for those who hope to live here, some of whom have already put in the significant time and effort to do so legally.\nIt pays no heed to the lives it touches.\nIf the order stands, a large number of foreign citizens who are already living in the U.S. legally will get a taste of the undocumented life and learn firsthand what it means to be unwanted, disrespected, and unable to leave without fear of deportation."}