{"url": "http://www.foxnews.com/us/2017/02/04/visa-holders-hurry-to-board-flights-to-us-amid-reprieve.html", "id": "266", "title": "Visa holders hurry to board flights to US amid reprieve", "text": "Visa holders from seven majority-Muslim countries affected by President Donald Trump's travel ban are hurrying to board U.S.-bound flights, fearing they might have only a slim window through which to enter the country after a federal judge temporarily blocked the ban.\n\nThose who could travel immediately were being urged to do so because of uncertainty over whether the Justice Department would be granted an emergency freeze of the order issued Friday by U.S. District Judge James Robart in Seattle.\n\nThe government on Saturday suspended enforcement of the week-old ban as it scurried to appeal Robart's order.\n\nRula Aoun, director of the Arab American Civil Rights League in Dearborn, Michigan, told The Detroit News that she knows of one family who intends to fly back from Egypt on Sunday and another woman there who is booking her flight back as soon as possible.", "authors": [], "publish_date": "2017-02-04", "source": "foxnews", "top_words": ["reprieve", "travel", "weekold", "amid", "usbound", "uncertainty", "ban", "holders", "judge", "window", "board", "flights", "woman", "urged", "hurry", "visa"], "summary": "Visa holders from seven majority-Muslim countries affected by President Donald Trump's travel ban are hurrying to board U.S.-bound flights, fearing they might have only a slim window through which to enter the country after a federal judge temporarily blocked the ban.\nThose who could travel immediately were being urged to do so because of uncertainty over whether the Justice Department would be granted an emergency freeze of the order issued Friday by U.S. District Judge James Robart in Seattle.\nThe government on Saturday suspended enforcement of the week-old ban as it scurried to appeal Robart's order.\nRula Aoun, director of the Arab American Civil Rights League in Dearborn, Michigan, told The Detroit News that she knows of one family who intends to fly back from Egypt on Sunday and another woman there who is booking her flight back as soon as possible."}