{"url": "http://www.foxnews.com/world/2017/02/08/pope-repeats-bridges-not-walls-after-trump-travel-ban.html", "id": "474", "title": "Pope repeats 'bridges not walls' after Trump travel ban", "text": "Pope Francis has repeated his appeal for people to build bridges of understanding instead of walls in his first, albeit indirect, comments since the Trump administration tried to impose a travel ban on people from seven mostly Muslim countries.\n\nFrancis made the comments during his weekly Wednesday catechism lesson, dedicated to the general Christian precepts of hope and forgiveness in forging peace.\n\nHe said: \"In the social and civil context as well, I appeal not to create walls but to build bridges. To not respond to evil with evil. To defeat evil with good, the offense with forgiveness. A Christian would never say 'you will pay for that.' Never. That is not a Christian gesture. An offense you overcome with forgiveness. To live in peace with everyone.\"", "authors": [], "publish_date": "2017-02-08", "source": "foxnews", "top_words": ["travel", "pope", "trump", "ban", "comments", "appeal", "repeats", "evil", "walls", "build", "offense", "bridges", "forgiveness", "weekly", "christian"], "summary": "Pope Francis has repeated his appeal for people to build bridges of understanding instead of walls in his first, albeit indirect, comments since the Trump administration tried to impose a travel ban on people from seven mostly Muslim countries.\nFrancis made the comments during his weekly Wednesday catechism lesson, dedicated to the general Christian precepts of hope and forgiveness in forging peace.\nHe said: \"In the social and civil context as well, I appeal not to create walls but to build bridges.\nTo not respond to evil with evil.\nTo defeat evil with good, the offense with forgiveness."}