{"url": "http://tech.fortune.cnn.com/2017/02/09/apple-ceo-tim-cook-donald-trump-travel-ban/", "id": "99", "title": "Apple CEO Tim Cook Does Not like President Trump's Travel Ban", "text": "Tim Cook does not like President Trump\u2019s travel ban.\n\nThe Apple (aapl) executive repeated his criticism for the ban while receiving an honorary doctorate at Scotland\u2019s University of Glasgow, BBC News reports.\n\n\u201cI wrote this letter, you probably read about it unless you\u2019re living underground, about the most recent executive order that was issued in the U.S.,\u201d Cook said according to BBC News, as he was responding to questions from students and staff at the University.\n\n\u201cWe have employees that secured a work visa, they brought family to the U.S., but happened to be outside the U.S. when the executive order was issued and all of a sudden their families were affected,\u201d he said. \u201cThey couldn\u2019t get back in. That\u2019s a crisis. You can imagine the stress.\u201d\n\nCook continued to say that if no one speaks out against it, it\u2019s \u201cas if we\u2019re agreeing, that we become a part of it. It\u2019s important to speak out.\u201d\n\nCook isn\u2019t the only tech CEO who\u2019s spoken out against the ban. The executive order, which prohibits immigrants from seven Muslim-majority countries from entering the United States for at least 90 days, and bars Syrian refugees indefinitely, has caused an outcry from Silicon Valley chiefs\u2014namely from Google (goog), Facebook (fb), Lyft, and Uber, and of course, Apple.", "authors": ["Madeline Farber"], "publish_date": "2017-02-09", "source": "cnn", "top_words": ["executive", "does", "travel", "cook", "wrote", "ban", "bbc", "order", "youre", "trumps", "ceo", "issued", "work", "tim", "apple", "president"], "summary": "Tim Cook does not like President Trump\u2019s travel ban.\nThe Apple (aapl) executive repeated his criticism for the ban while receiving an honorary doctorate at Scotland\u2019s University of Glasgow, BBC News reports.\n\u201cWe have employees that secured a work visa, they brought family to the U.S., but happened to be outside the U.S. when the executive order was issued and all of a sudden their families were affected,\u201d he said.\nIt\u2019s important to speak out.\u201dCook isn\u2019t the only tech CEO who\u2019s spoken out against the ban.\nThe executive order, which prohibits immigrants from seven Muslim-majority countries from entering the United States for at least 90 days, and bars Syrian refugees indefinitely, has caused an outcry from Silicon Valley chiefs\u2014namely from Google (goog), Facebook (fb), Lyft, and Uber, and of course, Apple."}